iBot/__init__.py
iBot/browser_activities.py
iBot/dataBase_activities.py
iBot/email_activities.py
iBot/excel_activities.py
iBot/file_images_folder_activities.py
iBot/files_activities.py
iBot/ocr_activities.py
iBot/robot_activities.py
iBot/screen_activities.py
iBot/system_activities.py
iBot/undetected_chromedriver.py
iBot/word_activities.py
iBotAutomation/__init__.py
iBotAutomation/browser_activities.py
iBotAutomation/dataBase_activities.py
iBotAutomation/email_activities.py
iBotAutomation/excel_activities.py
iBotAutomation/file_images_folder_activities.py
iBotAutomation/files_activities.py
iBotAutomation/ocr_activities.py
iBotAutomation/robot_activities.py
iBotAutomation/screen_activities.py
iBotAutomation/system_activities.py
iBotAutomation/undetected_chromedriver.py
iBotAutomation/word_activities.py
iBotAutomation-1.1.dist-info/METADATA
iBotAutomation-1.1.dist-info/WHEEL
iBotAutomation-1.1.dist-info/top_level.txt
iBotAutomation-1.1.dist-info/RECORD
