Metadata-Version: 2.1
Name: iBotAutomation
Version: 1.1
Summary: Python RPA library
Home-page: https://github.com/ecrespo66/ibot
Author: Enrique Crespo
Author-email: oname.dohe@gmail.com
License: [MIT](LICENSE-MIT)
Download-URL: https://github.com/ecrespo66/iBot-Automation/tarball/v0.2
Keywords: Python RPA,Bot,Automation
Platform: UNKNOWN
Classifier: Programming Language :: Python :: 3.3
Classifier: Programming Language :: Python :: 3.4
Classifier: Programming Language :: Python :: 3.5
Classifier: Programming Language :: Python :: 3.6
Classifier: Programming Language :: Python :: 3.7
Classifier: Programming Language :: Python :: 3.8
